rapid_assistant/__init__.py
rapid_assistant-0.0.1.dist-info/LICENSE
rapid_assistant-0.0.1.dist-info/METADATA
rapid_assistant-0.0.1.dist-info/WHEEL
rapid_assistant-0.0.1.dist-info/top_level.txt
rapid_assistant-0.0.1.dist-info/RECORD
